autopsypy/__init__.py
autopsypy/autopsypy.py
autopsypy-0.2.2.dist-info/LICENSE.txt
autopsypy-0.2.2.dist-info/METADATA
autopsypy-0.2.2.dist-info/WHEEL
autopsypy-0.2.2.dist-info/top_level.txt
autopsypy-0.2.2.dist-info/RECORD
