Metadata-Version: 2.1
Name: autopsypy
Version: 0.2.2
Summary: Automate PsychoPy experiments
Home-page: https://github.com/rlaboiss/autopsypy
Author: Rafael Laboissière
Author-email: rafael@laboissiere.net
License: GPL-3+
Project-URL: ChangeLog, https://github.com/rlaboiss/autopsypy/blob/main/CHANGELOG.md
Project-URL: Tracker, https://github.com/rlaboiss/autopsypy/issues
License-File: LICENSE.txt
Requires-Dist: pandas
